[
  {
    "pangrams": ["birlikte", "tebrikler"],
    "answers": [
      "bile",
      "belki",
      "biri",
      "birlikte",
      "bekle",
      "elbette",
      "beri",
      "bitti",
      "bebek",
      "belli",
      "bilir",
      "birileri",
      "tebrikler",
      "bill",
      "birer",
      "ekibi",
      "biter",
      "bilet",
      "tebrik",
      "bitir",
      "bilerek",
      "birlik",
      "bire"
    ],
    "middleLetter": "b",
    "validLetters": ["t", "e", "l", "k", "b", "i", "r"]
  },
  {
    "pangrams": ["zorunda"],
    "answers": [
      "orada",
      "anda",
      "zorunda",
      "ondan",
      "arada",
      "durun",
      "oradan",
      "orda",
      "odada",
      "onda",
      "ordu",
      "andan",
      "durdur",
      "ndan",
      "durdu",
      "donna",
      "duran",
      "zordur",
      "dana",
      "durdurun"
    ],
    "middleLetter": "d",
    "validLetters": ["z", "r", "n", "o", "a", "d", "u"]
  },
  {
    "pangrams": ["üzerinde", "üzerinden"],
    "answers": [
      "neden",
      "nerede",
      "nedir",
      "nereden",
      "edin",
      "üzerinde",
      "dedi",
      "eder",
      "üzerine",
      "eden",
      "üzere",
      "dedin",
      "nedeni",
      "deniz",
      "derin",
      "dene",
      "ederiz",
      "nerde",
      "eddie",
      "üzerinden",
      "nedenini",
      "nerden",
      "denen",
      "derdi",
      "derdin",
      "nden",
      "denir",
      "deri",
      "erdi",
      "denize",
      "ederdi",
      "dediniz",
      "düzen",
      "eninde",
      "düzine"
    ],
    "middleLetter": "e",
    "validLetters": ["z", "i", "d", "n", "r", "ü", "e"]
  },
  {
    "pangrams": ["değilsin"],
    "answers": [
      "değil",
      "neden",
      "dinle",
      "senden",
      "edin",
      "değildi",
      "değilsin",
      "dedi",
      "sende",
      "eden",
      "dedin",
      "deli",
      "elinde",
      "nedeni",
      "elde",
      "edildi",
      "dene",
      "elinden",
      "eddie",
      "değilse",
      "nedenle",
      "dediğini",
      "nedenini",
      "dediğin",
      "sendin",
      "denen",
      "dediği",
      "değildin",
      "edilen",
      "dile",
      "delil",
      "dediğine",
      "eninde"
    ],
    "middleLetter": "d",
    "validLetters": ["s", "d", "i", "l", "ğ", "e", "n"]
  },
  {
    "pangrams": ["boyunca"],
    "answers": [
      "bana",
      "bunu",
      "onun",
      "bunun",
      "bayan",
      "buna",
      "boyunca",
      "oyun",
      "baban",
      "oyunu",
      "uyan",
      "yana",
      "anna",
      "bunca",
      "onca",
      "banyo",
      "babana",
      "oyuncu",
      "oyuna",
      "nancy",
      "boyun",
      "oyunun"
    ],
    "middleLetter": "n",
    "validLetters": ["y", "n", "o", "c", "b", "u", "a"]
  },
  {
    "pangrams": ["günaydın"],
    "answers": [
      "aynı",
      "anda",
      "dünya",
      "yanında",
      "günaydın",
      "dünyanın",
      "adını",
      "yanına",
      "adına",
      "dünyada",
      "danny",
      "adın",
      "dünyayı",
      "yada",
      "dünyaya",
      "yana",
      "adında",
      "andy",
      "anna",
      "yangın",
      "andan",
      "yanı",
      "dayan",
      "ndan",
      "ayda",
      "ayın",
      "anında",
      "yandan",
      "dana",
      "aday",
      "yanından",
      "dünyadan"
    ],
    "middleLetter": "a",
    "validLetters": ["ü", "d", "g", "y", "a", "n", "ı"]
  },
  {
    "pangrams": ["haklısın"],
    "answers": [
      "sakın",
      "haklısın",
      "kısa",
      "haklı",
      "kalk",
      "kalan",
      "sıkı",
      "kalın",
      "salak",
      "kalsın",
      "akıllı",
      "aklını",
      "alakası",
      "akıl",
      "aklına",
      "alakalı",
      "kanı",
      "hakkı",
      "halk",
      "hank",
      "halka",
      "kalanını",
      "kanlı",
      "kanka",
      "kalanı",
      "hakkın",
      "hakkını",
      "halkın",
      "aklı",
      "sakla",
      "halkı"
    ],
    "middleLetter": "k",
    "validLetters": ["h", "ı", "n", "a", "s", "l", "k"]
  },

  {
    "pangrams": ["yardımcı"],
    "answers": [
      "yardım",
      "ayrıca",
      "adamı",
      "yardımcı",
      "adım",
      "adamım",
      "mıydı",
      "yarım",
      "mıyım",
      "aradı",
      "yardıma",
      "aradım",
      "ararım",
      "ayrı",
      "yarı",
      "yardımı",
      "adımı",
      "aydır",
      "cadı",
      "amacı",
      "yaradı",
      "aracı",
      "adamdı",
      "mıdır"
    ],
    "middleLetter": "ı",
    "validLetters": ["ı", "a", "y", "c", "d", "r", "m"]
  },
  {
    "pangrams": ["istediğim", "istediğimi"],
    "answers": [
      "dedim",
      "etti",
      "ettim",
      "istediğim",
      "dedi",
      "istedim",
      "istedi",
      "istemedim",
      "istemem",
      "isim",
      "sesi",
      "istediği",
      "istediğimi",
      "ismi",
      "ettiğim",
      "eddie",
      "ettiği",
      "dediğim",
      "sistemi",
      "eğitim",
      "etmesi",
      "demedim",
      "dediğimi",
      "dediği",
      "etmedi",
      "testi",
      "etmedim",
      "istemedi",
      "ettiğimi",
      "etmemi",
      "sistem",
      "iste",
      "simdi"
    ],
    "middleLetter": "i",
    "validLetters": ["d", "s", "ğ", "m", "e", "t", "i"]
  },

  {
    "pangrams": ["istediğim", "istediğimi"],
    "answers": [
      "dedim",
      "etti",
      "ettim",
      "istediğim",
      "dedi",
      "istedim",
      "istedi",
      "istemedim",
      "istemem",
      "isim",
      "sesi",
      "istediği",
      "istediğimi",
      "ismi",
      "ettiğim",
      "eddie",
      "ettiği",
      "dediğim",
      "sistemi",
      "eğitim",
      "etmesi",
      "demedim",
      "dediğimi",
      "dediği",
      "etmedi",
      "testi",
      "etmedim",
      "istemedi",
      "ettiğimi",
      "etmemi",
      "sistem",
      "iste",
      "simdi"
    ],
    "middleLetter": "i",
    "validLetters": ["d", "s", "ğ", "m", "e", "t", "i"]
  }
]
